scikit_recommender-0.1.1.dist-info/LICENSE
scikit_recommender-0.1.1.dist-info/top_level.txt
scikit_recommender-0.1.1.dist-info/WHEEL
scikit_recommender-0.1.1.dist-info/RECORD
scikit_recommender-0.1.1.dist-info/METADATA
skrec/run_config.py
skrec/version.py
skrec/__init__.py
skrec/recommender/base.py
skrec/recommender/CML.py
skrec/recommender/DENS.py
skrec/recommender/HGN.py
skrec/recommender/FREEDOM.py
skrec/recommender/LightGCL.py
skrec/recommender/SGAT.py
skrec/recommender/MGCN.py
skrec/recommender/SASRec.py
skrec/recommender/MultVAE.py
skrec/recommender/SelfCF.py
skrec/recommender/SLMRec.py
skrec/recommender/FPMC.py
skrec/recommender/__init__.py
skrec/recommender/BM3.py
skrec/recommender/CDAE.py
skrec/recommender/TransRec.py
skrec/recommender/GRU4RecPlus.py
skrec/recommender/Caser.py
skrec/recommender/LightGCN.py
skrec/recommender/Pop.py
skrec/recommender/LayerGCN.py
skrec/recommender/LATTICE.py
skrec/recommender/SRGNN.py
skrec/recommender/GRU4Rec.py
skrec/recommender/BPRMF.py
skrec/recommender/BERT4Rec/bert4rec_utils.py
skrec/recommender/BERT4Rec/modeling.py
skrec/recommender/BERT4Rec/bert4rec_gen_data.py
skrec/recommender/BERT4Rec/__init__.py
skrec/recommender/BERT4Rec/optimization.py
skrec/recommender/BERT4Rec/BERT4Rec.py
skrec/recommender/BERT4Rec/vocab.py
skrec/recommender/AOBPR/AOBPR.py
skrec/recommender/AOBPR/__init__.py
skrec/recommender/AOBPR/pyx_aobpr_func.cpython-310-x86_64-linux-gnu.so
skrec/utils/torch.py
skrec/utils/registry.py
skrec/utils/common.py
skrec/utils/tf2x.py
skrec/utils/__init__.py
skrec/utils/hyperopt.py
skrec/utils/tf1x.py
skrec/utils/py/evaluator.py
skrec/utils/py/decorator.py
skrec/utils/py/random.py
skrec/utils/py/__init__.py
skrec/utils/py/generic.py
skrec/utils/py/config.py
skrec/utils/py/batch_iterator.py
skrec/utils/py/cython/pyx_random.cpython-310-x86_64-linux-gnu.so
skrec/utils/py/cython/pyx_sort.cpython-310-x86_64-linux-gnu.so
skrec/utils/py/cython/pyx_utils.cpython-310-x86_64-linux-gnu.so
skrec/utils/py/cython/pyx_init.cpython-310-x86_64-linux-gnu.so
skrec/utils/py/cython/pyx_eval_matrix.cpython-310-x86_64-linux-gnu.so
skrec/utils/py/cython/__init__.py
skrec/io/movielens.py
