Metadata-Version: 2.1
Name: scikit-recommender
Version: 0.1.1
Summary: A science toolkit for recommender systems
Home-page: https://github.com/ZhongchuanSun/scikit-recommender
Author: ZhongchuanSun
Author-email: zhongchuansun@gmail.com
License: UNKNOWN
Platform: Windows
Platform: Linux
Platform: Mac OS
Classifier: Development Status :: 4 - Beta
Classifier: Intended Audience :: Developers
Classifier: Intended Audience :: Science/Research
Classifier: License :: OSI Approved :: MIT License
Classifier: Operating System :: Microsoft :: Windows
Classifier: Operating System :: Unix
Classifier: Operating System :: MacOS
Classifier: Programming Language :: Python
Classifier: Programming Language :: Python :: 3.6
Classifier: Programming Language :: Python :: 3.7
Classifier: Programming Language :: Python :: 3.8
Classifier: Programming Language :: Python :: 3.9
Classifier: Programming Language :: Python :: 3.10
Classifier: Programming Language :: Python :: Implementation :: CPython
Classifier: Topic :: Scientific/Engineering
Classifier: Topic :: Scientific/Engineering :: Artificial Intelligence
Classifier: Topic :: Scientific/Engineering :: Information Analysis
Classifier: Topic :: Software Development :: Libraries
Classifier: Topic :: Software Development :: Libraries :: Python Modules
Requires-Python: >=3.6
Requires-Dist: numpy >=1.17
Requires-Dist: scipy
Requires-Dist: pandas
Requires-Dist: colorama
Requires-Dist: hyperopt
